wyge/__init__.py
wyge/agents/__init__.py
wyge/agents/base_agent.py
wyge/agents/prebuilt_agents.py
wyge/agents/prebuilt_agents0.py
wyge/agents/react_agent.py
wyge/memory/__init__.py
wyge/memory/basic_memory.py
wyge/models/__init__.py
wyge/models/openai.py
wyge/prompts/__init__.py
wyge/prompts/react_prompt.py
wyge/tools/__init__.py
wyge/tools/base_tool.py
wyge/tools/prebuilt_tools.py
wyge/tools/python_repl.py
wyge/tools/raw_functions.py
wyze-1.0.0.dist-info/METADATA
wyze-1.0.0.dist-info/WHEEL
wyze-1.0.0.dist-info/top_level.txt
wyze-1.0.0.dist-info/RECORD
